plutarch/__init__.py
plutarch/chat.py
plutarch/version.py
plutarch-0.1.1.dist-info/METADATA
plutarch-0.1.1.dist-info/WHEEL
plutarch-0.1.1.dist-info/top_level.txt
plutarch-0.1.1.dist-info/RECORD
