Metadata-Version: 2.1
Name: plutarch
Version: 0.1.1
Summary: Python client for the Plutarch API
